[
{
    "model": "statuses.status",
    "pk": 1,
    "fields": {
        "name": "New",
        "timestamp": "2024-03-16T08:11:56.105Z"
    }
},
{
    "model": "statuses.status",
    "pk": 2,
    "fields": {
        "name": "In work",
        "timestamp": "2024-03-16T08:12:10.272Z"
    }
},
{
    "model": "statuses.status",
    "pk": 3,
    "fields": {
        "name": "On testing",
        "timestamp": "2024-03-16T08:12:24.080Z"
    }
},
{
    "model": "statuses.status",
    "pk": 4,
    "fields": {
        "name": "Completed",
        "timestamp": "2024-03-16T08:13:22.383Z"
    }
}
]
